jsonConverter/__init__.py
jsonConverter/errors.py
jsonConverter/htmltable.py
jsonConverter-1.0.3.dist-info/LICENSE
jsonConverter-1.0.3.dist-info/METADATA
jsonConverter-1.0.3.dist-info/WHEEL
jsonConverter-1.0.3.dist-info/top_level.txt
jsonConverter-1.0.3.dist-info/RECORD
