Metadata-Version: 2.1
Name: jsonConverter
Version: 1.0.3
Summary: Json converter
Home-page: https://github.com/gp2kumar/jsonconverter
Author: prgarre
Author-email: garrepradeepkumar@gmail.com
License: UNKNOWN
Platform: UNKNOWN
Classifier: Programming Language :: Python :: 3
Classifier: License :: OSI Approved :: MIT License
Classifier: Operating System :: OS Independent
Requires-Python: >=3.5
Requires-Dist: jinja2
Requires-Dist: beautifulsoup4
